setup.cfg
setup.py
utest.py
utest.egg-info/PKG-INFO
utest.egg-info/SOURCES.txt
utest.egg-info/dependency_links.txt
utest.egg-info/entry_points.txt
utest.egg-info/top_level.txt