Metadata-Version: 1.1
Name: utest
Version: 0.0.1
Summary: utest is a tiny unit testing library for Python.
Home-page: https://github.com/gwk/utest
Author: George King
Author-email: george.w.king@gmail.com
License: CC0
Keywords: testing
Platform: UNKNOWN
Classifier: Development Status :: 4 - Beta
Classifier: Environment :: Console
Classifier: Intended Audience :: Developers
Classifier: License :: CC0 1.0 Universal (CC0 1.0) Public Domain Dedication
Classifier: Programming Language :: Python :: 3 :: Only
Classifier: Topic :: Software Development :: Testing
